asimov_modules/__init__.py
asimov_modules-0.0.0.dist-info/METADATA
asimov_modules-0.0.0.dist-info/WHEEL
asimov_modules-0.0.0.dist-info/top_level.txt
asimov_modules-0.0.0.dist-info/RECORD
